[{"letter":"gdfg","from":"Ramin","to":"Alexandr","time":"2024/7/1 - 19:45:34","id":5},{"letter":"dfgdfg","from":"Alexandr","to":"Ramin","time":"2024/7/1 - 19:50:54","id":2},{"letter":"gdfgdfg","from":"Ramin","to":"Alexandr","time":"2024/7/1 - 19:54:17","chat":"RaminandAlexandr","id":3},{"letter":"dfgdf","from":"Alexandr","to":"Ramin","time":"2024/7/1 - 19:54:18","chat":"RaminandAlexandr","id":4},{"letter":"gdfgdfggdfgf","from":"Ramin","to":"Alexandr","time":"2024/7/1 - 19:54:19","chat":"RaminandAlexandr","id":5},{"letter":"dfgdfgdfgfd","from":"Alexandr","to":"Ramin","time":"2024/7/1 - 19:54:21","chat":"RaminandAlexandr","id":6},{"letter":"gdfgdfggdfgfgdfgfd","from":"Ramin","to":"Alexandr","time":"2024/7/1 - 19:54:22","chat":"RaminandAlexandr","id":7},{"letter":"dfgdfgdfgfd","from":"Alexandr","to":"Ramin","time":"2024/7/1 - 19:54:23","chat":"RaminandAlexandr","id":8},{"letter":"dfgdfgdfgfddfg","from":"Alexandr","to":"Ramin","time":"2024/7/1 - 19:54:24","chat":"RaminandAlexandr","id":9},{"letter":"dfgdfgdfgfddfg","from":"Alexandr","to":"Ramin","time":"2024/7/1 - 19:54:25","chat":"RaminandAlexandr","id":10},{"letter":"dfgdfgdfgfddfgdfg","from":"Alexandr","to":"Ramin","time":"2024/7/1 - 19:54:26","chat":"RaminandAlexandr","id":11},{"letter":"gdfgdfggdfgfgdfgfdgdfggdfg","from":"Ramin","to":"Alexandr","time":"2024/7/1 - 19:54:27","chat":"RaminandAlexandr","id":12},{"letter":"dfgdfgdfgfddfgdfg","from":"Alexandr","to":"Ramin","time":"2024/7/1 - 19:54:27","chat":"RaminandAlexandr","id":13},{"letter":"dfgdfgdfgfddfgdfg","from":"Alexandr","to":"Ramin","time":"2024/7/1 - 19:54:28","chat":"RaminandAlexandr","id":14},{"letter":"","from":"Ramin","to":"Alexandr","time":"2024/7/1 - 20:23:35","chat":"RaminandAlexandr","id":15},{"letter":"","from":"Ramin","to":"Alexandr","time":"2024/7/1 - 20:24:48","chat":"RaminandAlexandr","id":16},{"letter":"","from":"Alexandr","to":"Ramin","time":"2024/7/1 - 20:24:57","chat":"RaminandAlexandr","id":17},{"letter":"","from":"Ramin","to":"Alexandr","time":"2024/7/1 - 20:25:20","chat":"RaminandAlexandr","id":18},{"letter":"","from":"Ramin","to":"Alexandr","time":"2024/7/1 - 20:31:25","chat":"RaminandAlexandr","id":19},{"letter":"","from":"Ramin","to":"Alexandr","time":"2024/7/1 - 20:32:33","chat":"RaminandAlexandr","id":20},{"letter":"","from":"Ramin","to":"Alexandr","time":"2024/7/1 - 20:34:29","chat":"RaminandAlexandr","id":21},{"letter":"","from":"Ramin","to":"Alexandr","time":"2024/7/1 - 20:35:0","chat":"RaminandAlexandr","id":22},{"letter":"","from":"Ramin","to":"Alexandr","time":"2024/7/1 - 20:53:38","chat":"RaminandAlexandr","id":23},{"letter":"","from":"Ramin","to":"Alexandr","time":"2024/7/1 - 20:54:17","chat":"RaminandAlexandr","id":24},{"letter":"","from":"Ramin","to":"Alexandr","time":"2024/7/1 - 20:55:34","chat":"RaminandAlexandr","id":25},{"letter":"","from":"Ramin","to":"Alexandr","time":"2024/7/1 - 20:57:33","chat":"RaminandAlexandr","id":26}]